markovsoccer/__init__.py
markovsoccer/config.py
markovsoccer/dtmc.py
markovsoccer/extended_spadl.py
markovsoccer/features.py
markovsoccer/prism.py
markovsoccer/team_model.py
markovsoccer/util.py
markovsoccer-0.1.2.dist-info/WHEEL
markovsoccer-0.1.2.dist-info/METADATA
markovsoccer-0.1.2.dist-info/RECORD
