Metadata-Version: 2.1
Name: markovsoccer
Version: 0.1.2
Summary: Implementation of the construction of Markov models representing the offensive style of play of soccer teams, and analysis based on these models.
Home-page: https://github.com/JeroenClijmans/markovsoccer
License: MIT
Keywords: soccer,football,sports analytics
Author: Jeroen Clijmans
Author-email: jeroen.clijmans@student.kuleuven.be
Requires-Python: >=3.8,<3.11
Classifier: License :: OSI Approved :: MIT License
Classifier: Operating System :: OS Independent
Classifier: Programming Language :: Python :: 3
Classifier: Programming Language :: Python :: 3.8
Classifier: Programming Language :: Python :: 3.9
Classifier: Programming Language :: Python :: 3.10
Classifier: Programming Language :: Python :: 3
Requires-Dist: matplotlib (>=3.6.0,<4.0.0)
Requires-Dist: matplotsoccer (>=0.0.8,<0.0.9)
Requires-Dist: pandas (>=1.5.0,<2.0.0)
Requires-Dist: seaborn (>=0.12.0,<0.13.0)
Requires-Dist: setuptools (>=65.4.1,<66.0.0)
Requires-Dist: sklearn (>=0.0,<0.1)
Requires-Dist: socceraction (==1.2.3)
Requires-Dist: statsbombpy (>=1.5.0,<2.0.0)
Requires-Dist: tables (>=3.7.0,<4.0.0)
Requires-Dist: tqdm (>=4.64.1,<5.0.0)
Project-URL: Repository, https://github.com/JeroenClijmans/markovsoccer
